pysentry/__init__.py
pysentry/_internal.cpython-313-x86_64-linux-gnu.so
pysentry_rs-0.4.0.dist-info/METADATA
pysentry_rs-0.4.0.dist-info/WHEEL
pysentry_rs-0.4.0.dist-info/entry_points.txt
pysentry_rs-0.4.0.dist-info/licenses/LICENSE
pysentry_rs-0.4.0.dist-info/RECORD
