Metadata-Version: 2.4
Name: pysentry-rs
Version: 0.4.0
Classifier: Development Status :: 4 - Beta
Classifier: Intended Audience :: Developers
Classifier: License :: OSI Approved :: MIT License
Classifier: Programming Language :: Rust
Classifier: Programming Language :: Python :: Implementation :: CPython
Classifier: Programming Language :: Python :: 3.9
Classifier: Programming Language :: Python :: 3.10
Classifier: Programming Language :: Python :: 3.11
Classifier: Programming Language :: Python :: 3.12
Classifier: Programming Language :: Python :: 3.13
Classifier: Programming Language :: Python :: 3.14
Classifier: Topic :: Security
Classifier: Topic :: Software Development :: Libraries :: Python Modules
License-File: LICENSE
Summary: Security vulnerability auditing tool for Python packages
Author-email: nyudenkov <nyudenkov@pm.me>
License: MIT
Requires-Python: >=3.9
Project-URL: Homepage, https://github.com/nyudenkov/pysentry
Project-URL: Issues, https://github.com/nyudenkov/pysentry/issues
Project-URL: Repository, https://github.com/nyudenkov/pysentry
